psanalyzer/__init__.py
psanalyzer/database.py
psanalyzer/fs.py
psanalyzer/main.py
psanalyzer/queries.py
psanalyzer/util.py
psanalyzer-0.1.0.dist-info/METADATA
psanalyzer-0.1.0.dist-info/WHEEL
psanalyzer-0.1.0.dist-info/entry_points.txt
psanalyzer-0.1.0.dist-info/RECORD
