Metadata-Version: 2.1
Name: psanalyzer
Version: 0.1.0
Summary: A tool which turns project repo into a SQLite3 database. Use it to query various info about it.
Author: Bohdan Vanieiev
Author-email: warchantua@aptiv.com
Requires-Python: >=3.7,<4.0
Classifier: Programming Language :: Python :: 3
Classifier: Programming Language :: Python :: 3.7
Classifier: Programming Language :: Python :: 3.8
Classifier: Programming Language :: Python :: 3.9
Classifier: Programming Language :: Python :: 3.10
Classifier: Programming Language :: Python :: 3.11
Requires-Dist: click (>=8.1.3,<9.0.0)
Requires-Dist: memoization (>=0.4.0,<0.5.0)
Requires-Dist: sqlalchemy (>=2.0.17,<3.0.0)
Requires-Dist: tabulate (>=0.9.0,<0.10.0)
Requires-Dist: tqdm (>=4.65.0,<5.0.0)
